cpf_cnpj/__init__.py
cpf_cnpj/cpf_cnpj.py
cpf_cnpj/utils.py
cpf_cnpj/tests/__init__.py
cpf_cnpj/tests/tests.py
validate_cpf_cnpj-0.1.2.dist-info/LICENSE
validate_cpf_cnpj-0.1.2.dist-info/METADATA
validate_cpf_cnpj-0.1.2.dist-info/WHEEL
validate_cpf_cnpj-0.1.2.dist-info/top_level.txt
validate_cpf_cnpj-0.1.2.dist-info/zip-safe
validate_cpf_cnpj-0.1.2.dist-info/RECORD
